online_node2vec/__init__.py
online_node2vec/experiments.py
online_node2vec/data/__init__.py
online_node2vec/data/n2v_embedding_handler.py
online_node2vec/data/tennis_handler.py
online_node2vec/evaluation/__init__.py
online_node2vec/evaluation/distance_computer.py
online_node2vec/evaluation/ndcg_computer.py
online_node2vec/offline/__init__.py
online_node2vec/offline/node2vec.py
online_node2vec/offline/offline_node2vec_model.py
online_node2vec/online/__init__.py
online_node2vec/online/hash_utils.py
online_node2vec/online/npw2v.py
online_node2vec/online/online_node2vec_models.py
online_node2vec/online/w2v_learners.py
online_node2vec/online/walk_sampling.py
online_node2vec-0.1.1.dist-info/LICENSE
online_node2vec-0.1.1.dist-info/METADATA
online_node2vec-0.1.1.dist-info/WHEEL
online_node2vec-0.1.1.dist-info/top_level.txt
online_node2vec-0.1.1.dist-info/RECORD
