Metadata-Version: 2.1
Name: online-node2vec
Version: 0.1.1
Summary: Node Embeddings in Dynamic Graphs
Home-page: https://github.com/ferencberes/online-node2vec
Author: Ferenc Beres
Author-email: fberes@info.ilab.sztaki.hu
License: UNKNOWN
Keywords: graph,research,embeddings,representation learning,dynamic graph,temporal network,mention graph,twitter
Platform: UNKNOWN
Requires-Python: >=3.6
Requires-Dist: twittertennis
Requires-Dist: networkx
Requires-Dist: pandas
Requires-Dist: numpy
Requires-Dist: scipy
Requires-Dist: gensim
Requires-Dist: sympy
Requires-Dist: plotly
Requires-Dist: tqdm
Requires-Dist: python-Levenshtein
